Workbook

Sheet Relatório & Contas Preencher
A1: Disponível | B1: Total Receita | C1: Gasto | E1: REGRAS
A2: =+SUM(C10:C90)-SUM(D10:D90) -> -10 | B2: =+SUM(C10:C90) -> 0 | C2: =+SUBTOTAL(9,D10:D90) -> 10 | E2: 1. Preencher esta folha. Onde encontrares 'Inf. Obrigatória', tens de preencher obrigatoriamente. Se tiveres alguma dúvida podes ligar-nos (Rita Cassiano - 965 083 885 | Pedro Batalha - 927 691 709)
E3: 2. No final desta tabela podes consultar um quadro com os vários códigos. Todas as rúbricas têm de ter um código associado.
E4: 3. Em cada linha da coluna 'Código', encontras uma seta. Se clicares nessa seta, encontras uma lista dos códigos. Clica no código que se aplica à receita / gasto.
E5: 4. A descrição do código preenche automaticamente. Não tens de escrever nada.
F7: Seleccionar Cod.
C8: Inf. Obrigatória | D8: Inf. Obrigatória | E8: Inf. Obrigatória | F8: Inf. Obrigatória | G8: Preenchimento Automático
A9: Data | B9: Nº recibo | C9: Receitas | D9: Despesas | E9: Descrição | F9: Código | G9: Descrição Cod.
A10: - | B10: - | C10: ='Dados Iniciais Preencher'!C22 -> --//--//-- | D10: - | E10: Orçamento de Campo | F10: - | G10: =IFERROR((VLOOKUP($F10,Apoio!$O:$P,2,FALSE)),"") -> -
B11: 1 | C11: 0 | D11: 10 | E11: Material FDS Campo - exemplo apagar | F11: 1.1 | G11: =IFERROR((VLOOKUP($F11,Apoio!$O:$P,2,FALSE)),"") -> FDS Campo | Deslocações FDS Campo
G12: =IFERROR((VLOOKUP($F12,Apoio!$O:$P,2,FALSE)),"")
G13: =IFERROR((VLOOKUP($F13,Apoio!$O:$P,2,FALSE)),"")
G14: =IFERROR((VLOOKUP($F14,Apoio!$O:$P,2,FALSE)),"")
G16: =IFERROR((VLOOKUP($F16,Apoio!$O:$P,2,FALSE)),"")
G18: =IFERROR((VLOOKUP($F18,Apoio!$O:$P,2,FALSE)),"")
G19: =IFERROR((VLOOKUP($F19,Apoio!$O:$P,2,FALSE)),"")
G20: =IFERROR((VLOOKUP($F20,Apoio!$O:$P,2,FALSE)),"")
G21: =IFERROR((VLOOKUP($F21,Apoio!$O:$P,2,FALSE)),"")
G22: =IFERROR((VLOOKUP($F22,Apoio!$O:$P,2,FALSE)),"")
G23: =IFERROR((VLOOKUP($F23,Apoio!$O:$P,2,FALSE)),"")
G24: =IFERROR((VLOOKUP($F24,Apoio!$O:$P,2,FALSE)),"")
G25: =IFERROR((VLOOKUP($F25,Apoio!$O:$P,2,FALSE)),"")
... G138: =IFERROR((VLOOKUP($F138,Apoio!$O:$P,2,FALSE)),"")
A139: Legenda
A141: Campo | B141: Código
A142: Deslocações (FDS Preparação) | B142: 1.1
A143: Alimentação (FDS Preparação) | B143: 1.2
A144: Correio (Divulgação Campo) | B144: 2.1
A145: Telemóveis (Divulgação Campo) | B145: 2.2
A146: Compras Gerais | B146: 3.1.1
A147: Talho | B147: 3.1.2
A148: Pão | B148: 3.1.3
A149: Frutas & Legumes | B149: 3.1.4
A150: Diversos | B150: 3.1.5
A151: Gastos com Participantes | B151: 3.2.1
A152: Gastos Master | B152: 3.2.2
... A160: Outros | B160: 3.6
A161: Registos Criminais | B161: 45358

Sheet Dados Iniciais Preencher
B11: Rúbricas
B12: Campo:
B13: Data: | C13: =IFERROR((VLOOKUP($C$12,Apoio!E2:I17,5,FALSE)),"--//--//--") -> --//--//--
B14: Local:
B16: Direção | C16: Descrição
B17: Director/a | C17: {=IFERROR((INDEX(Contactos!A:A,MATCH('Dados Iniciais Preencher'!$C$12&'Dados Iniciais Preencher'!$B17,Contactos!D:D,0),)),"--//--//--")} -> --//--//--
B18: Adjunto/a | C18: {=IFERROR((INDEX(Contactos!A:A,MATCH('Dados Iniciais Preencher'!$C$12&'Dados Iniciais Preencher'!$B18,Contactos!D:D,0),)),"--//--//--")} -> --//--//--
B19: Mamã | C19: {=IFERROR((INDEX(Contactos!A:A,MATCH('Dados Iniciais Preencher'!$C$12&'Dados Iniciais Preencher'!$B19,Contactos!D:D,0),)),"--//--//--")} -> --//--//--
B21: Valores de Referência | C21: =IF((C12=""),"",C12) | D21: Aranhiços a Camaleões
B22: Saldo Inicial | C22: =+IFERROR(IFS($C$12="Mosquitos I",2930,$C$12="Mosquitos II",2930,$C$12="Aranhiços I",3280,$C$12="Aranhiços II",3280,$C$12="Aranhiços III",3280,$C$12="Melgas I",3400,$C$12="Melgas II",3400,$C$12="Tremelgas I",3400,$C$12="Tremelgas II",3400,$C$12="Tremelgas III",3400,$C$12="Camaleões I",3630,$C$12="Camaleões II",3630,$C$12="Cifa",B10,$C$12="Trolhas",B10,$C$12="Cegonhas",B10),"--//--//--") -> --//--//-- | D22: 2400
B23: 1. Até ao Campo | C23: =+C24+C25 -> 10 | D23: =D24+D25 -> #REF!
B24: 1. Fim de Semana de Preparação | C24: =+'Valores Ref. Verão '!I4 -> 10 | D24: =+#REF!+#REF!+#REF! -> #REF!
B25: 2. Divulgação do Campo | C25: =+'Valores Ref. Verão '!I7 -> 0 | D25: 30
B26: 3. Campo | C26: =+C27+C28+C29+C30+C31+C32 -> 0 | D26: =D22-D23 -> #REF!
B27: 3.1 - Alimentação | C27: =+'Valores Ref. Verão '!I11 -> 0 | D27: =+#REF!+#REF!+#REF!+#REF!+#REF! -> #REF!
B28: 3.2 - Transportes | C28: =+'Valores Ref. Verão '!I17 -> 0 | D28: =+#REF!+#REF!+#REF!+#REF! -> #REF!
B29: 3.3 - Material | C29: =+'Valores Ref. Verão '!I22 -> 0 | D29: =+#REF!+#REF! -> #REF!
B30: 3.4 - Gastos Animadores | C30: =+'Valores Ref. Verão '!I25 -> 0 | D30: =+#REF!+#REF! -> #REF!
B31: 3.5 - Farmácia | C31: =+'Valores Ref. Verão '!I28 -> 0 | D31: 20
B32: 3.6 - Outros | C32: =+'Valores Ref. Verão '!I29 -> 0 | D32: 10
B33: 3.7 - Registos Criminais | C33: =+'Valores Ref. Verão '!I30 -> 0
B34: Saldo Final | C34: =IFERROR((C22-C24-C25-C27-C28-C29-C30-C31-C32-C33),"") | D34: =+D24+D25+D27+D28+D29+D30+D31+D32+#REF! -> #REF!

Sheet Valores Ref. Verão 
B1: Valores de Referência | C1: Mosquitos | D1: Aranhiços | E1: Melgas | F1: Tremelgas | G1: Camaleões | I1: Gastos Reais
A2: Cod. | B2: Saldo Inicial | C2: 2930 | D2: 3280 | E2: 3400 | F2: 3400 | G2: 3630 | I2: =+'Dados Iniciais Preencher'!C22 -> --//--//--
B3: 1. Até ao Campo | C3: =C4+C7 -> 395 | D3: =D4+D7 -> 395 | E3: =E4+E7 -> 395 | F3: =F4+F7 -> 395 | G3: =G4+G7 -> 395 | I3: =I4+I7 -> 10
B4: 1. Fim de Semana de Preparação | C4: =+C5+C6 -> 345 | D4: =+D5+D6 -> 345 | E4: =+E5+E6 -> 345 | F4: =+F5+F6 -> 345 | G4: =+G5+G6 -> 345 | I4: =+I5+I6 -> 10
A5: 1.1 | B5: 1.1 - Deslocações | C5: 200 | D5: 200 | E5: 200 | F5: 200 | G5: 200 | I5: =+SUMIF('Relatório & Contas Preencher'!F:F,'Valores Ref. Verão '!$A5,'Relatório & Contas Preencher'!D:D) -> 10
A6: 1.2 | B6: 1.2 - Alimentação | C6: 145 | D6: 145 | E6: 145 | F6: 145 | G6: 145 | I6: =+SUMIF('Relatório & Contas Preencher'!F:F,'Valores Ref. Verão '!$A6,'Relatório & Contas Preencher'!D:D) -> 0
B7: 2. Divulgação do Campo | C7: 50 | D7: 50 | E7: 50 | F7: 50 | G7: 50 | I7: =+I8+I9 -> 0
A8: 2.1 | B8: 2.1 - Correio | C8: 32.94 | D8: 32.94 | E8: 32.94 | F8: 32.94 | G8: 32.94 | I8: =+SUMIF('Relatório & Contas Preencher'!F:F,'Valores Ref. Verão '!$A8,'Relatório & Contas Preencher'!D:D) -> 0
A9: 2.2 | B9: 2.2 - Telemóveis | C9: 0 | D9: 0 | E9: 0 | F9: 0 | G9: 0 | I9: =+SUMIF('Relatório & Contas Preencher'!F:F,'Valores Ref. Verão '!$A9,'Relatório & Contas Preencher'!D:D) -> 0
B10: 3. Campo | C10: =SUM(C11,C17,C22,C25,C28,C29+C30) -> 2480 | D10: =SUM(D11,D17,D22,D25,D28,D29+D30) -> 2830 | E10: =SUM(E11,E17,E22,E25,E28,E29+E30) -> 2950 | F10: =SUM(F11,F17,F22,F25,F28,F29+F30) -> 2950 | G10: =SUM(G11,G17,G22,G25,G28,G29+G30) -> 3180 | I10: =SUM(I11,I17,I22,I25,I28,I29) -> 0
B11: 3.1. Alimentação | C11: =SUM(C12:C16) -> 1700 | D11: =SUM(D12:D16) -> 2050 | E11: =SUM(E12:E16) -> 2170 | F11: =SUM(F12:F16) -> 2170 | G11: =SUM(G12:G16) -> 2400 | I11: =+I12+I13+I14+I15+I16 -> 0
A12: 3.1.1 | B12: 3.1.1 - Compras Gerais | C12: =970+25 -> 995 | D12: 1140 | E12: 1170 | F12: 1170 | G12: 1215 | I12: =+SUMIF('Relatório & Contas Preencher'!F:F,'Valores Ref. Verão '!$A12,'Relatório & Contas Preencher'!D:D) -> 0
A13: 3.1.2 | B13: 3.1.2 - Talho | C13: 265 | D13: 340 | E13: 390 | F13: 390 | G13: 505 | I13: =+SUMIF('Relatório & Contas Preencher'!F:F,'Valores Ref. Verão '!$A13,'Relatório & Contas Preencher'!D:D) -> 0
A14: 3.1.3 | B14: 3.1.3 - Pão | C14: 160 | D14: 250 | E14: 270 | F14: 270 | G14: 300 | I14: =+SUMIF('Relatório & Contas Preencher'!F:F,'Valores Ref. Verão '!$A14,'Relatório & Contas Preencher'!D:D) -> 0
A15: 3.1.4 | B15: 3.1.4 - Frutas & Legumes | C15: 245 | D15: 285 | E15: 305 | F15: 305 | G15: 345 | I15: =+SUMIF('Relatório & Contas Preencher'!F:F,'Valores Ref. Verão '!$A15,'Relatório & Contas Preencher'!D:D) -> 0
A16: 3.1.5 | B16: 3.1.5 - Diversos | C16: 35 | D16: 35 | E16: 35 | F16: 35 | G16: 35 | I16: =+SUMIF('Relatório & Contas Preencher'!F:F,'Valores Ref. Verão '!$A16,'Relatório & Contas Preencher'!D:D) -> 0
B17: 3.2. Transportes / Deslocações no Campo | C17: =SUM(C18:C21) -> 185 | D17: =SUM(D18:D21) -> 185 | E17: =SUM(E18:E21) -> 185 | F17: =SUM(F18:F21) -> 185 | G17: =SUM(G18:G21) -> 185 | I17: =+I18+I19+I20+I21 -> 0
A18: 3.2.1 | B18: 3.2.1 - Gastos com Participantes | C18: 0 | D18: 0 | E18: 0 | F18: 0 | G18: 0 | I18: =+SUMIF('Relatório & Contas Preencher'!F:F,'Valores Ref. Verão '!$A18,'Relatório & Contas Preencher'!D:D) -> 0
A19: 3.2.2 | B19: 3.2.2 - Gastos Master | C19: 55 | D19: 55 | E19: 55 | F19: 55 | G19: 55 | I19: =+SUMIF('Relatório & Contas Preencher'!F:F,'Valores Ref. Verão '!$A19,'Relatório & Contas Preencher'!D:D) -> 0
A20: 3.2.3 | B20: 3.2.3 - Gastos Kangoo | C20: 100 | D20: 100 | E20: 100 | F20: 100 | G20: 100 | I20: =+SUMIF('Relatório & Contas Preencher'!F:F,'Valores Ref. Verão '!$A20,'Relatório & Contas Preencher'!D:D) -> 0
A21: 3.2.4 | B21: 3.2.4 - Transporte Jesuita | C21: 30 | D21: 30 | E21: 30 | F21: 30 | G21: 30 | I21: =+SUMIF('Relatório & Contas Preencher'!F:F,'Valores Ref. Verão '!$A21,'Relatório & Contas Preencher'!D:D) -> 0
B22: 3.3. Material | C22: =+C23+C24 -> 155 | D22: =+D23+D24 -> 155 | E22: =+E23+E24 -> 155 | F22: =+F23+F24 -> 155 | G22: =+G23+G24 -> 155 | I22: =+I23+I24 -> 0
A23: 3.3.1 | B23: 3.3.1 - Gás (Botijas & Petromax & Camisas) | C23: 65 | D23: 65 | E23: 65 | F23: 65 | G23: 65 | I23: =+SUMIF('Relatório & Contas Preencher'!F:F,'Valores Ref. Verão '!$A23,'Relatório & Contas Preencher'!D:D) -> 0
A24: 3.3.2 | B24: 3.3.2 - Papelaria, Chineses, Material para Jogos, Sisal | C24: 90 | D24: 90 | E24: 90 | F24: 90 | G24: 90 | I24: =+SUMIF('Relatório & Contas Preencher'!F:F,'Valores Ref. Verão '!$A24,'Relatório & Contas Preencher'!D:D) -> 0
B25: 3.4. Gastos Animadores | C25: =+C26+C27 -> 310 | D25: =+D26+D27 -> 310 | E25: =+E26+E27 -> 310 | F25: =+F26+F27 -> 310 | G25: =+G26+G27 -> 310 | I25: =+I26+I27 -> 0
A26: 3.4.1 | B26: 3.4.1 - Deslocações (Carros Animadores Ida & Volta) | C26: 310 | D26: 310 | E26: 310 | F26: 310 | G26: 310 | I26: =+SUMIF('Relatório & Contas Preencher'!F:F,'Valores Ref. Verão '!$A26,'Relatório & Contas Preencher'!D:D) -> 0
A27: 3.4.2 | B27: 3.4.2 - Telemóveis | C27: 0 | D27: 0 | E27: 0 | F27: 0 | G27: 0 | I27: =+SUMIF('Relatório & Contas Preencher'!F:F,'Valores Ref. Verão '!$A27,'Relatório & Contas Preencher'!D:D) -> 0
A28: 3.5 | B28: 3.5. Farmácia | C28: 50 | D28: 50 | E28: 50 | F28: 50 | G28: 50 | I28: =+SUMIF('Relatório & Contas Preencher'!F:F,'Valores Ref. Verão '!$A28,'Relatório & Contas Preencher'!D:D) -> 0
A29: 3.6 | B29: 3.6. Outros | C29: 0 | D29: 0 | E29: 0 | F29: 0 | G29: 0 | I29: =+SUMIF('Relatório & Contas Preencher'!F:F,'Valores Ref. Verão '!$A29,'Relatório & Contas Preencher'!D:D) -> 0
A30: 3.7 | B30: 3.7. Registos Criminais | C30: 80 | D30: 80 | E30: 80 | F30: 80 | G30: 80 | I30: =+SUMIF('Relatório & Contas Preencher'!F:F,'Valores Ref. Verão '!$A30,'Relatório & Contas Preencher'!D:D) -> 0
B31: Margem de Segurança | C31: =1.098*50 -> 54.9 | D31: =1.098*50 -> 54.9 | E31: =1.098*50 -> 54.9 | F31: =1.098*50 -> 54.9 | G31: =1.098*50 -> 54.9 | I31: =+SUMIF('Relatório & Contas Preencher'!F:F,'Valores Ref. Verão '!$A31,'Relatório & Contas Preencher'!D:D) -> 0
B32: TOTAL | C32: =+C4+C7+C11+C17+C22+C25+C28+C29+C30+C31 -> 2929.9 | D32: =+D4+D7+D11+D17+D22+D25+D28+D29+D30+D31 -> 3279.9 | E32: =+E4+E7+E11+E17+E22+E25+E28+E29+E30+E31 -> 3399.9 | F32: =+F4+F7+F11+F17+F22+F25+F28+F29+F30+F31 -> 3399.9 | G32: =+G4+G7+G11+G17+G22+G25+G28+G29+G30+G31 -> 3629.9 | I32: =+I4+I7+I11+I17+I22+I25+I28+I29+I30+I31 -> 10
B34: Nota: Não entram para estas contas o CamtilShop

Sheet Feedback
A1: NOTAS GERAIS | B1: O FEEDBACK DA TESOURARIA no final do verão vai ter em conta as seguintes NOTAS GERAIS:
A2: 1. Até ao Campo | B2: O adjunto deve preparar os seus documentos de suporte / valores de referência para começar a utilizá-los logo no fim-de-semana de campo.
A3: 1.1. Fim de Semana de Preparação | B3: É muito importante todos os animadores irem ao fim-de-semana. Aqui, contamos com uma boa gestão do adjunto para arranjar / organizar o local e boleias ( i.e., tentar arranjar uma casa na zona centro (idealmente) e coordenar os carros para que tragam o mínimo possível de carros). O Loureto, em Coimbra, é sempre uma boa última alternativa, mas têm que perguntar com antecedência.
A4: 2. Divulgação do Campo | B4: O orçamento tem em conta o envio da carta de campo via CTT, contudo também há a possibilidade de enviar a carta por email.
A5: 3. Campo | B5: Ao iniciar o campo, o adjunto deve ter as contas dos pontos 1. e 2. todas fechadas e registadas. Para uma boa gestão orçamental, o adjunto deve ter no seu cartão um montante / valor igual ou superior ao valor de referência indicado para o campo.
A6: 3.1. Alimentação | B6: O valor de referência tem em conta os gastos com alimentação feitos nos últimos anos, ajustados à inflação deste ano. Esse valor é uma referência para cada escalão. No entanto, sabemos que os locais de campo não são iguais e que os custos podem variar até dentro do mesmo escalão. Portanto, é muito importante que o adjunto esteja ciente das despesas da cozinha (e.g., saber quanto vai custar o pão, acompanhar as despesas do supermercado, talho, frutas e legumes...), para que não seja surpreendido com o valor gasto no final do campo. Sugestão: façam um orçamento com antecedência, em conjunto com a cozinha, antes de irem ao supermercado.
A7: 3.2. Transportes | B7: Gerir bem as saídas de campo é essencial para evitar "gastar" tempo e dinheiro desnecessários com a Kangoo. É importante planear as compras e antecipar as necessidades (i.e., tanto em termos de material como de alimentação) para uma boa gestão. Dessa forma, a equipa pode passar mais tempo em campo.
A8: 3.3. Material | B8: O material de papelaria é da vossa conta, no entanto, é possível que tenham sobras de outros campos. Em relação ao gás, a regra é deixar sempre duas botijas de Petromax e uma de fogão cheias para cada campo.
A9: 3.4. Gastos Animadores | B9: Aqui aconselhamos que se faça uma boa gestão de quem vai ao pré-campo e quem fica para ir com os miúdos. Normalmente, quem está mais longe do local de campo fica para levar os miúdos no comboio.
A10: 3.5. Farmácia | B10: Mais uma vez, lembrem-se que é da responsabilidade de cada campo repor aquilo que gastou em farmácia. Atenção: cada farmácia tem um stock inicial e deve ter uma lista com a contagem desse stock. Assim, tudo o que vocês comprarem de fora dessa lista não tem de ser reposto.
A11: 3.6. Outros | B11: Esta rúbrica existe para algum gasto que vocês não saibam bem alocar.
A12: Margem de Segurança | B12: A margem de 50€ alocada a cada campo serve para "não se contar com esse dinheiro". Se excederem os plafons acima definidos esta poderá acautelar os mesmos.

Sheet Contactos
A1: Nome completo | B1: Cargo | C1: Campo
A2: Migalha | B2: Director/a | C2: Mosquitos I | D2: =C2&B2 -> Mosquitos IDirector/a
A3: Manel Góis | B3: Adjunto/a | C3: Mosquitos I | D3: =C3&B3 -> Mosquitos IAdjunto/a
A4: Magali | B4: Mamã | C4: Mosquitos I | D4: =C4&B4 -> Mosquitos IMamã
A5: Afonso Mestre | B5: Director/a | C5: Mosquitos II | D5: =C5&B5 -> Mosquitos IIDirector/a
A6: Jinho | B6: Adjunto/a | C6: Mosquitos II | D6: =C6&B6 -> Mosquitos IIAdjunto/a
A7: Rita Cassiano Santos | B7: Mamã | C7: Mosquitos II | D7: =C7&B7 -> Mosquitos IIMamã
A8: Duarte Líbano Monteiro | B8: Director/a | C8: Aranhiços I | D8: =C8&B8 -> Aranhiços IDirector/a
A9: Henrique Gil | B9: Adjunto/a | C9: Aranhiços I | D9: =C9&B9 -> Aranhiços IAdjunto/a
A10: Maria Resende | B10: Mamã | C10: Aranhiços I | D10: =C10&B10 -> Aranhiços IMamã
A11: Manel Brito e Faro | B11: Director/a | C11: Aranhiços II | D11: =C11&B11 -> Aranhiços IIDirector/a
A12: António Toscano Rico | B12: Adjunto/a | C12: Aranhiços II | D12: =C12&B12 -> Aranhiços IIAdjunto/a
A13: Constança Cravo | B13: Mamã | C13: Aranhiços II | D13: =C13&B13 -> Aranhiços IIMamã
... A34: Sofia Mira Vaz | B34: Mamã | C34: Camaleões I | D34: =C34&B34 -> Camaleões IMamã

Sheet Valores Ref. Inverno
B1: Preço por Campo | C1: 60 | D1: 35 | E1: 60
B2: Nº de Participantes | C2: 69 | D2: 35 | E2: 23
B3: Valores de Referência | C3: CIFA | D3: Trolhas | E3: Cegonhas | G3: Gastos Reais | J3: Diferêncial
A4: Cod. | B4: Saldo Inicial | C4: =+C2*C1 -> 4140 | D4: =+D2*D1 -> 1225 | E4: =+E2*E1+5 -> 1385 | G4: =+'Dados Iniciais Preencher'!C22 -> --//--//-- | J4: =+G4 -> --//--//--
B5: 1. Até ao Campo | C5: =C6+C9 -> 0 | D5: =D6+D9 -> 0 | E5: =E6+E9 -> 100 | G5: =G6+G9 -> 10 | J5: =+$E5-G5 -> 90
B6: 1. Fim de Semana de Preparação | C6: =+C7+C8 -> 0 | D6: 0 | E6: =+E7+E8 -> 100 | G6: =+G7+G8 -> 10 | J6: =+$E6-G6 -> 90
A7: 1.1 | B7: 1.1 - Deslocações | C7: 0 | D7: 180 | E7: 100 | G7: =+SUMIF('Relatório & Contas Preencher'!F:F,'Valores Ref. Inverno'!$A7,'Relatório & Contas Preencher'!D:D) -> 10 | J7: =+$E7-G7 -> 90
A8: 1.2 | B8: 1.2 - Alimentação | C8: 0 | D8: 120 | E8: 0 | G8: =+SUMIF('Relatório & Contas Preencher'!F:F,'Valores Ref. Inverno'!$A8,'Relatório & Contas Preencher'!D:D) -> 0 | J8: =+$E8-G8 -> 0
B9: 2. Divulgação do Campo | C9: =+C10+C11 -> 0 | D9: 0 | E9: =+E10+E11 -> 0 | G9: =+G10+G11 -> 0 | J9: =+$E9-G9 -> 0
A10: 2.1 | B10: 2.1 - Correio | C10: 0 | D10: 30 | E10: 0 | G10: =+SUMIF('Relatório & Contas Preencher'!F:F,'Valores Ref. Inverno'!$A10,'Relatório & Contas Preencher'!D:D) -> 0 | J10: =+$E10-G10 -> 0
A11: 2.2 | B11: 2.2 - Telemóveis | C11: 0 | D11: 0 | E11: 0 | G11: =+SUMIF('Relatório & Contas Preencher'!F:F,'Valores Ref. Inverno'!$A11,'Relatório & Contas Preencher'!D:D) -> 0 | J11: =+$E11-G11 -> 0
B12: 3. Campo | C12: =C4-C5 -> 4140 | D12: =D4-D5 -> 1225 | E12: =E4-E5 -> 1285 | G12: =+G13+G19+G23+G26+G29+G30 -> 0 | J12: =$E12-G12 -> 1285
B13: 3.1 - Alimentação | C13: =+C14+C15+C16+C17+C18 -> 1000 | D13: =+D14+D15+D16+D17+D18 -> 1000 | E13: =+E14+E15+E16+E17+E18 -> 660 | G13: =+G14+G15+G16+G17+G18 -> 0 | J13: =+$E13-G13 -> 660
A14: 3.1.1 | B14: 3.1.1 - Compras Gerais | C14: 600 | D14: 600 | E14: 600 | G14: =+SUMIF('Relatório & Contas Preencher'!F:F,'Valores Ref. Inverno'!$A14,'Relatório & Contas Preencher'!D:D) -> 0 | J14: =+$E14-G14 -> 600
A15: 3.1.2 | B15: 3.1.2 - Talho | C15: 150 | D15: 150 | E15: 0 | G15: =+SUMIF('Relatório & Contas Preencher'!F:F,'Valores Ref. Inverno'!$A15,'Relatório & Contas Preencher'!D:D) -> 0 | J15: =+$E15-G15 -> 0
A16: 3.1.3 | B16: 3.1.3 - Pão | C16: 100 | D16: 100 | E16: 60 | G16: =+SUMIF('Relatório & Contas Preencher'!F:F,'Valores Ref. Inverno'!$A16,'Relatório & Contas Preencher'!D:D) -> 0 | J16: =+$E16-G16 -> 60
A17: 3.1.4 | B17: 3.1.4 - Frutas & Legumes | C17: 120 | D17: 120 | E17: 0 | G17: =+SUMIF('Relatório & Contas Preencher'!F:F,'Valores Ref. Inverno'!$A17,'Relatório & Contas Preencher'!D:D) -> 0 | J17: =+$E17-G17 -> 0
A18: 3.1.5 | B18: 3.1.5 - Diversos | C18: 30 | D18: 30 | E18: 0 | G18: =+SUMIF('Relatório & Contas Preencher'!F:F,'Valores Ref. Inverno'!$A18,'Relatório & Contas Preencher'!D:D) -> 0 | J18: =+$E18-G18 -> 0
B19: 3.2 - Transportes | C19: =+C20+C21+C22 -> 1850 | D19: =+D20+D21+D22 -> 0 | E19: =+E20+E21+E22 -> 450 | G19: =+G20+G21+G22 -> 0 | J19: =+$E19-G19 -> 450
A20: 3.2.1 | B20: 3.2.1 - Gastos com Participantes | C20: 1600 | D20: 0 | E20: 0 | G20: =+SUMIF('Relatório & Contas Preencher'!F:F,'Valores Ref. Inverno'!$A20,'Relatório & Contas Preencher'!D:D) -> 0 | J20: =+$E20-G20 -> 0
A21: 3.2.2 | B21: 3.2.2 - Gastos Master | C21: 0 | D21: 0 | E21: 450 | G21: =+SUMIF('Relatório & Contas Preencher'!F:F,'Valores Ref. Inverno'!$A21,'Relatório & Contas Preencher'!D:D) -> 0 | J21: =+$E21-G21 -> 450
A22: 3.2.3 | B22: 3.2.3 - Gastos Kangoo | C22: 250 | D22: 0 | E22: 0 | G22: =+SUMIF('Relatório & Contas Preencher'!F:F,'Valores Ref. Inverno'!$A22,'Relatório & Contas Preencher'!D:D) -> 0 | J22: =+$E22-G22 -> 0
B23: 3.3 - Material | C23: =+C24+C25 -> 100 | D23: =+D24+D25 -> 50 | E23: =+E24+E25 -> 30 | G23: =+G24+G25 -> 0 | J23: =+$E23-G23 -> 30
A24: 3.3.1 | B24: 3.3.1 - Gás (Botijas & Petromax & Camisas) | C24: 30 | D24: 30 | E24: 5 | G24: =+SUMIF('Relatório & Contas Preencher'!F:F,'Valores Ref. Inverno'!$A24,'Relatório & Contas Preencher'!D:D) -> 0 | J24: =+$E24-G24 -> 5
A25: 3.3.2 | B25: 3.3.2 - Papelaria, Chineses, Material para Jogos, Sisal | C25: 70 | D25: 20 | E25: 25 | G25: =+SUMIF('Relatório & Contas Preencher'!F:F,'Valores Ref. Inverno'!$A25,'Relatório & Contas Preencher'!D:D) -> 0 | J25: =+$E25-G25 -> 25
B26: 3.4 - Gastos Animadores | C26: =+C27+C28 -> 250 | D26: =+D27+D28 -> 100 | E26: =+E27+E28 -> 80 | G26: =+G27+G28 -> 0 | J26: =+$E26-G26 -> 80
A27: 3.4.1 | B27: 3.4.1 - Deslocações | C27: 250 | D27: 100 | E27: 80 | G27: =+SUMIF('Relatório & Contas Preencher'!F:F,'Valores Ref. Inverno'!$A27,'Relatório & Contas Preencher'!D:D) -> 0 | J27: =+$E27-G27 -> 80
A28: 3.4.2 | B28: 3.4.2 - Telemóveis | C28: 0 | D28: 0 | E28: 0 | G28: =+SUMIF('Relatório & Contas Preencher'!F:F,'Valores Ref. Inverno'!$A28,'Relatório & Contas Preencher'!D:D) -> 0 | J28: =+$E28-G28 -> 0
A29: 3.5 | B29: 3.5 - Farmácia/ Seguros | C29: 150 | D29: 30 | E29: 0 | G29: =+SUMIF('Relatório & Contas Preencher'!F:F,'Valores Ref. Inverno'!$A29,'Relatório & Contas Preencher'!D:D) -> 0 | J29: =+$E29-G29 -> 0
A30: 3.6 | B30: 3.6 - Outros/Estadia | C30: =600+50 -> 650 | D30: 30 | E30: 30 | G30: =+SUMIF('Relatório & Contas Preencher'!F:F,'Valores Ref. Inverno'!$A30,'Relatório & Contas Preencher'!D:D) -> 0 | J30: =+$E30-G30 -> 30
B31: Margem de Segurança | C31: =+C12-C13-C19-C23-C26-C29-C30 -> 140 | D31: =+D12-D13-D19-D23-D26-D29-D30 -> 15 | E31: =+E12-E13-E19-E23-E26-E29-E30 -> 35 | I31: Saldo
B32: TOTAL | C32: =+C6+C9+C13+C19+C23+C26+C29+C30+C31 -> 4140 | D32: =+D6+D9+D13+D19+D23+D26+D29+D30+D31 -> 1225 | E32: =+E6+E9+E13+E19+E23+E26+E29+E30+E31 -> 1385 | G32: =+G6+G9+G13+G19+G23+G26+G29+G30+G31 -> 10 | I32: =IFERROR((G4-G32),"")
B34: Nota: Não entram para estas contas o CamtilShop

Sheet Apoio
A1: Ordem | B1: Escalão | D1: Ordem | E1: Escalão | F1: Escalão | G1: Ordem | H1: Local de Campo | I1: Datas dos Campos | K1: 1ª vez animar (x) | L1: Tipo de Animador | M1: Ordem | O1: Cod. | P1: Desc. Cod. | Q1: Códigos
A2: 1 | B2: Mosquito | D2: 1 | E2: Mosquitos I | F2: Mosquito | G2: 1 | I2: 30 Julho - 6 Agosto | K2: Sim | L2: Director/a | M2: 1 | O2: - | P2: - | Q2: -
A3: 2 | B3: Aranhiço | D3: 1 | E3: Mosquitos II | F3: Mosquito | G3: 1.1 | I3: 19 - 26 Agosto | K3: Não | L3: Adjunto/a | M3: 2 | O3: 1.1 | P3: FDS Campo | Deslocações FDS Campo | Q3: 1.1 - Deslocações
A4: 3 | B4: Melga | D4: 2 | E4: Aranhiços I | F4: Aranhiço | G4: 2.1 | I4: 17 - 26 Julho | L4: Mamã | M4: 3 | O4: 1.2 | P4: FDS Campo | Alimentação | Q4: 1.2 - Alimentação
A5: 4 | B5: Tremelga | D5: 2 | E5: Aranhiços II | F5: Aranhiço | G5: 2.2 | I5: 28 Julho - 6 Agosto | L5: Capelão | M5: 4 | O5: 2.1 | P5: Divulgação | Correio | Q5: 2.1 - Correio
A6: 5 | B6: Camaleão | D6: 2 | E6: Aranhiços III | F6: Aranhiço | G6: 2.3 | I6: 8 - 17 Agosto | L6: Capelinho | M6: 4.1 | O6: 2.2 | P6: Divulgação | Telemóveis | Q6: 2.2 - Telemóveis
A7: 6 | B7: CIFA | D7: 3 | E7: Melgas I | F7: Melga | G7: 3.1 | I7: 28 Julho - 6 Agosto | L7: Tia/o | M7: 5 | O7: 3.1.1 | P7: Alimentação | Compras Gerais | Q7: 3.1.1 - Compras Grandes
A8: 7 | B8: Trolhas | D8: 3 | E8: Melgas II | F8: Melga | G8: 3.2 | I8: 8 - 17 Agosto | L8: Livre | M8: 6 | O8: 3.1.2 | P8: Alimentação | Talho | Q8: 3.1.2 - Talho
A9: 8 | B9: Cegonhas | D9: 3 | E9: Melgas III | F9: Melga | G9: 3.3 | I9: 19 - 28 Agosto | L9: Equipa | M9: 7 | O9: 3.1.3 | P9: Alimentação | Pão | Q9: 3.1.3 - Pão
D10: 4 | E10: Tremelgas I | F10: Tremelga | G10: 4.1 | I10: 17 - 26 Julho | O10: 3.1.4 | P10: Alimentação | Frutas & Legumes | Q10: 3.1.4 - Frutas & Legumes
D11: 4 | E11: Tremelgas II | F11: Tremelga | G11: 4.2 | I11: 19 - 28 Agosto | O11: 3.1.5 | P11: Alimentação | Diversos | Q11: 3.1.5 - Diversos
D12: 4 | E12: Tremelgas III | F12: Tremelga | G12: 4.3 | I12: --//--//-- | O12: 3.2.1 | P12: Transportes | Gastos com Participantes | Q12: 3.2.1 - Gastos com Participantes
D13: 5 | E13: Camaleões I | F13: Camaleão | G13: 44682 | I13: 8 - 17 Agosto | O13: 3.2.2 | P13: Transportes | Gastos Master | Q13: 3.2.2 - Gastos Master
D14: 6 | E14: Camaleões II | F14: Camaleão | G14: 44683 | I14: --//--//-- | O14: 3.2.3 | P14: Transportes | Gastos Kangoo | Q14: 3.2.3 - Gastos Kangoo
D15: 7 | E15: CIFA | F15: CIFA | G15: 6 | I15: 27 Março - 1 Abril | O15: 3.2.4 | P15: Transportes | Transporte Jesuita | Q15: 3.2.4 - Transporte Jesuita
D16: 8 | E16: Trolhas | F16: Trolhas | G16: 7 | I16: 27 Março - 1 Abril | O16: 3.3.1 | P16: Material | Gás (Botijas & Petromax & Camisas) | Q16: 3.3.1 - Gás (Botijas & Petromax & Camisas)
E17: Cegonhas | F17: Cegonhas | G17: 8 | I17: 3 - 7 Junho | O17: 3.3.2 | P17: Material | Papelaria, Chineses, Material para Jogos, Sisal | Q17: 3.3.2 - Papelaria, Chineses, Material para Jogos, Sisal
O18: 3.4.1 | P18: Gast. Anim. | Deslocações Animadores | Q18: 3.4.1 - Deslocações
O19: 3.4.2 | P19: Gast. Anim. | Telemóvel | Q19: 3.4.2 - Telemóveis
O20: 3.5 | P20: Farmácia | Q20: 3.5 - Farmácia
O21: 3.6 | P21: Outros | Q21: 3.6 - Outros
O22: 3.7 | P22: Registos Criminais | Q22: 3.7 - Registos Criminais
